dsw2to3/__init__.py
dsw2to3/__main__.py
dsw2to3/cli.py
dsw2to3/config.py
dsw2to3/consts.py
dsw2to3/errors.py
dsw2to3/logger.py
dsw2to3/connection/__init__.py
dsw2to3/connection/mongo.py
dsw2to3/connection/postgres.py
dsw2to3/connection/s3storage.py
dsw2to3/migration/__init__.py
dsw2to3/migration/common.py
dsw2to3/migration/entitites.py
dsw2to3/migration/registry.py
dsw2to3/migration/wizard.py
dsw2to3-1.0.2.dist-info/LICENSE
dsw2to3-1.0.2.dist-info/METADATA
dsw2to3-1.0.2.dist-info/WHEEL
dsw2to3-1.0.2.dist-info/entry_points.txt
dsw2to3-1.0.2.dist-info/top_level.txt
dsw2to3-1.0.2.dist-info/RECORD
