Metadata-Version: 2.1
Name: dsw2to3
Version: 1.0.2
Summary: CLI tool to support migration from DSW 2.14 to DSW 3.0
Home-page: https://github.com/ds-wizard/dsw2to3
Author: Marek Suchánek
License: Apache License 2.0
Keywords: dsw migration database upgrade
Platform: UNKNOWN
Classifier: License :: OSI Approved :: Apache Software License
Classifier: Programming Language :: Python
Classifier: Topic :: Database
Classifier: Topic :: Utilities
Requires-Python: >=3.6, <4
Requires-Dist: click
Requires-Dist: minio
Requires-Dist: pymongo
Requires-Dist: PyYAML
Requires-Dist: psycopg2
Requires-Dist: tenacity
